corelink/__init__.py
corelink/corelink.py
corelink/resources/Proto.py
corelink/resources/__init__.py
corelink/resources/control.py
corelink/resources/processing.py
corelink/resources/reqs.py
corelink/resources/variables.py
corelink-0.0.5.dist-info/METADATA
corelink-0.0.5.dist-info/WHEEL
corelink-0.0.5.dist-info/licenses/LICENSE
corelink-0.0.5.dist-info/RECORD
