Metadata-Version: 2.1
Name: Corelink
Version: 0.0.5
Summary: Client for connecting to Corelink server.
Project-URL: Homepage, https://corelink.hpc.nyu.edu
Author-email: Joe Braha <jbraha@nyu.edu>
License: MIT License
Classifier: License :: OSI Approved :: MIT License
Classifier: Operating System :: OS Independent
Classifier: Programming Language :: Python :: 3
Requires-Python: >=3.7
Requires-Dist: websockets
